Metadata-Version: 2.1
Name: textoter
Version: 0.5
Summary: Textoter is a simple application that sends SMS using a phone connected via Bluetooth
Home-page: https://github.com/agardelein/textoter
Author: Arnaud Gardelein
Author-email: arnaud@oscopy.org
License: UNKNOWN
Project-URL: Tracker, https://github.com/agardelein/textoter/issues
Keywords: gtk sms mms bluetooth phone send texto
Platform: UNKNOWN
Classifier: Programming Language :: Python :: 3
Classifier: License :: OSI Approved :: GNU General Public License v3 (GPLv3)
Classifier: Topic :: Communications :: Telephony
Classifier: Topic :: Desktop Environment :: Gnome
Classifier: Intended Audience :: End Users/Desktop
Requires-Python: >=3
